bioeq/__init__.py
bioeq/cli.py
bioeq/crossover2x2.py
bioeq/parallel.py
bioeq/replicate_crossover.py
bioeq/validation.py
bioeq-0.1.4.dist-info/LICENSE
bioeq-0.1.4.dist-info/METADATA
bioeq-0.1.4.dist-info/WHEEL
bioeq-0.1.4.dist-info/entry_points.txt
bioeq-0.1.4.dist-info/RECORD
