Metadata-Version: 2.3
Name: bioeq
Version: 0.1.4
Summary: A Python package for performing bioequivalence calculations and analysis.
License: MIT
Author: Shaun Porwal
Author-email: shaun.porwal@gmail.com
Requires-Python: >=3.10
Classifier: License :: OSI Approved :: MIT License
Classifier: Programming Language :: Python :: 3
Classifier: Programming Language :: Python :: 3.10
Classifier: Programming Language :: Python :: 3.11
Classifier: Programming Language :: Python :: 3.12
Classifier: Programming Language :: Python :: 3.13
Requires-Dist: numpy (>=2.2.1,<3.0.0)
Requires-Dist: polars (>=1.18.0,<2.0.0)
Requires-Dist: pyarrow (>=19.0.0,<20.0.0)
Requires-Dist: scipy (>=1.15.0,<2.0.0)
Requires-Dist: statsmodels (>=0.14.4,<0.15.0)
